exceltoxml/__init__.py
exceltoxml/converter.py
exceltoxml/core/__init__.py
exceltoxml/core/entity.py
exceltoxml/core/excel_converter.py
exceltoxml/core/json_converter.py
exceltoxml/core/xml_converter.py
exceltoxml/utils/__init__.py
exceltoxml/utils/file_utils.py
mfgwhitebox-0.0.9.dist-info/METADATA
mfgwhitebox-0.0.9.dist-info/WHEEL
mfgwhitebox-0.0.9.dist-info/entry_points.txt
mfgwhitebox-0.0.9.dist-info/top_level.txt
mfgwhitebox-0.0.9.dist-info/RECORD
