Metadata-Version: 2.4
Name: mfgwhitebox
Version: 0.0.9
Summary: A package to convert between Excel and XML files.
Home-page: https://github.com/hedaima/excel-xml-converter
Author: liumao0917
Author-email: liumao0917@gmail.com
Classifier: Programming Language :: Python :: 3
Classifier: License :: OSI Approved :: MIT License
Classifier: Operating System :: OS Independent
Requires-Python: >=3.6
Requires-Dist: openpyxl
Requires-Dist: lxml
Dynamic: author
Dynamic: author-email
Dynamic: classifier
Dynamic: description
Dynamic: description-content-type
Dynamic: home-page
Dynamic: requires-dist
Dynamic: requires-python
Dynamic: summary
